{
   "basics":{
     "name":"ahalya",
     "email":"gundaahalya@gmail.com",
     "mobile":"+91-8897232514"
   },
   "career":{
     "Info":"to pursue a challenging career and be a part of progressive organization that given scope to enhance my knowledge and utilising my skill towards the growth of organization"
   },
   "education":[{
     "degree":"b.tech",
     "institute":"pscmr",
     "data":["2019-2015"]
     },
     {
     "degree":"inter",
     "institute":"vj jr college",
     "data":["2015-2013"]
     },
     {
       "degree":"ssc",
     "institute":"aravinda model achool",
     "data":["2013-2012"]

     }
   ],
   "acheivements":[
     {
       "name":"Awarded as <b> 1 <sup>st</sup> prize </b> in <q>self-defence</q>"

     },
     {
      "name":"Got <strong>1<sup>st</sup> prize </strong> for <q> PPT presentation </q>"

     }

   ],
   "skills":[
     {
       "name":"programming languages",
       "data":["C","Java","Python","C++"]
     },
    {
         "name":"data bases",
         "data":["mysql","oracle"]
       },
       {
            "name":"Web Technologies",
            "data":["HTML","CSS","JavaScript"]
          },
          {
               "name":"Libraries and frameworks",
               "data":["jQuery","codeIgniter"]
             }
   ]
}
